ltxpdflinks/__init__.py
ltxpdflinks/__main__.py
ltxpdflinks/_extractor.py
ltxpdflinks/_linkconverter.py
ltxpdflinks/_lplxexporter.py
ltxpdflinks-0.1.2.dist-info/entry_points.txt
ltxpdflinks-0.1.2.dist-info/LICENSE
ltxpdflinks-0.1.2.dist-info/WHEEL
ltxpdflinks-0.1.2.dist-info/METADATA
ltxpdflinks-0.1.2.dist-info/RECORD
