Metadata-Version: 2.1
Name: ltxpdflinks
Version: 0.1.2
Summary: Extract links in PDF graphics for inclusion in LaTeX documents
Home-page: https://github.com/phfaist/ltxpdflinks
License: MIT
Author: Philippe Faist
Author-email: philippe.faist@bluewin.ch
Requires-Python: >=3.7,<4.0
Classifier: Development Status :: 4 - Beta
Classifier: License :: OSI Approved :: MIT License
Classifier: Programming Language :: Python :: 3
Classifier: Programming Language :: Python :: 3.7
Classifier: Programming Language :: Python :: 3.8
Requires-Dist: PyPDF2 (>=1.26.0,<2.0.0)
Requires-Dist: colorlog (>=6.0.0a4,<7.0.0)
Project-URL: Repository, https://github.com/phfaist/ltxpdflinks
